wkdhash/__init__.py
wkdhash/__main__.py
wkdhash/cli_convert.py
wkdhash/wkdhash.py
wkdhash-0.1.0.dist-info/LICENSE
wkdhash-0.1.0.dist-info/METADATA
wkdhash-0.1.0.dist-info/WHEEL
wkdhash-0.1.0.dist-info/entry_points.txt
wkdhash-0.1.0.dist-info/RECORD
