Metadata-Version: 2.3
Name: wkdhash
Version: 0.1.0
Summary: Calculate WKD (Web-Key-Directory) UID Hashes for OpenGPG UIDs
License: MIT
Keywords: wkd,openpgp,gpg
Author: Gregor Vollmer
Author-email: git@dynamic-noise.net
Requires-Python: >=3.11
Classifier: Development Status :: 5 - Production/Stable
Classifier: Environment :: Console
Classifier: Intended Audience :: Developers
Classifier: License :: OSI Approved :: MIT License
Classifier: Programming Language :: Python :: 3.11
Classifier: Programming Language :: Python :: 3.12
Classifier: Programming Language :: Python :: 3.13
Classifier: Topic :: Software Development :: Libraries
Classifier: Typing :: Typed
Requires-Dist: z-base-32 (>=0.1.4,<0.2.0)
Project-URL: Homepage, https://github.com/gregorv/wkdhash
Project-URL: Repository, https://github.com/gregorv/wkdhash
